nmap/__init__.py
nmap/nmap.py
nust_nmap-2.1.1.dist-info/licenses/LICENSE
tests/__init__.py
nust_nmap-2.1.1.dist-info/METADATA
nust_nmap-2.1.1.dist-info/WHEEL
nust_nmap-2.1.1.dist-info/top_level.txt
nust_nmap-2.1.1.dist-info/RECORD
