Metadata-Version: 2.4
Name: nust-nmap
Version: 2.1.1
Summary: A comprehensive Python wrapper for nmap with enhanced features
Home-page: https://github.com/codeNinja62/nust-nmap
Author: Sameer Ahmed
Author-email: Sameer Ahmed <sameer.cs@proton.me>
License: MIT
Project-URL: Homepage, https://github.com/codeNinja62/nust-nmap
Project-URL: Repository, https://github.com/codeNinja62/nust-nmap
Requires-Python: >=3.8
License-File: LICENSE
Requires-Dist: xmltodict>=0.13.0
Requires-Dist: psutil>=5.6.7
Dynamic: author
Dynamic: home-page
Dynamic: license-file
Dynamic: requires-python
